{"acc":[
  { "school": "Maryland",
    "cost": 12500,
    "mascot": "Terps" },
  { "school": "Duke",
    "cost": 25000,
    "mascot": "Blue Devils" },
  { "school": "Wake Forest",
    "cost": 8000,
    "mascot": "Demon Deacons" },
  { "school": "North Carolina",
    "cost": 21500,
    "mascot": "Tar Heels" },
  { "school": "Virginia",
    "cost": 14000,
    "mascot": "Cavaliers" },
  { "school": "Clemson",
    "cost": 10000,
    "mascot": "Tigers" },
  { "school": "NC State",
    "cost": 9000,
    "mascot": "Wolfpack" },
  { "school": "Florida State",
    "cost": 7500,
    "mascot": "Seminoles" },
  { "school": "Georgia Tech",
    "cost": 6000,
    "mascot": "Yellow Jackets" }
]}